ii0703_ejemplo_pypi_20250609/__init__.py
ii0703_ejemplo_pypi_20250609/main.py
ii0703_ejemplo_pypi_20250609-0.0.1.dist-info/METADATA
ii0703_ejemplo_pypi_20250609-0.0.1.dist-info/WHEEL
ii0703_ejemplo_pypi_20250609-0.0.1.dist-info/entry_points.txt
ii0703_ejemplo_pypi_20250609-0.0.1.dist-info/top_level.txt
ii0703_ejemplo_pypi_20250609-0.0.1.dist-info/RECORD
