Metadata-Version: 2.4
Name: ii0703_ejemplo_pypi_20250609
Version: 0.0.1
Summary: Un paquete de ejemplo que instala una calculadora con Tkinter.
Author-email: Mauricio Andres Zamora Hernandez <mauricio.zamorahernandez.ucr@gmail.com>
Classifier: Programming Language :: Python :: 3
Classifier: License :: OSI Approved :: MIT License
Classifier: Operating System :: OS Independent
Classifier: Topic :: Education
Requires-Python: >=3.7
